jetson_nlp_monitor/__init__.py
jetson_nlp_monitor/main.py
jetson_nlp_monitor/prompts.py
jetson_nlp_monitor-2025.12.21140514.dist-info/METADATA
jetson_nlp_monitor-2025.12.21140514.dist-info/WHEEL
jetson_nlp_monitor-2025.12.21140514.dist-info/top_level.txt
jetson_nlp_monitor-2025.12.21140514.dist-info/RECORD
