Metadata-Version: 2.4
Name: jetson-nlp-monitor
Version: 2025.12.21140514
Summary: A new package that processes user queries about system performance and resource usage on Nvidia Jetson boards. It takes natural language input, such as a request for current GPU utilization or memory
Author-email: jetson-nlp-monitor <hi@eugene.plus>
License: MIT
Project-URL: Homepage, https://github.com/chigwell/jetson-nlp-monitor
Requires-Python: >=3.9
Requires-Dist: langchain-llm7>=0.0.0
Requires-Dist: llmatch-messages>=0.0.0
Requires-Dist: langchain-core>=0.3.0
